requests_async/__init__.py
requests_async/client.py
requests_async-0.2.4.dist-info/licenses/LICENSE
requests_async-0.2.4.dist-info/METADATA
requests_async-0.2.4.dist-info/WHEEL
requests_async-0.2.4.dist-info/top_level.txt
requests_async-0.2.4.dist-info/RECORD
