Metadata-Version: 2.4
Name: requests-async
Version: 0.2.4
Summary: Simple async HTTP client with requests-like interface, powered by httpx
Author: requests-async contributors
License-Expression: MIT
Project-URL: Homepage, https://github.com/yourusername/requests-async
Project-URL: Bug Reports, https://github.com/yourusername/requests-async/issues
Project-URL: Source, https://github.com/yourusername/requests-async
Project-URL: Documentation, https://github.com/yourusername/requests-async#readme
Keywords: http,async,requests,client,httpx,asyncio
Classifier: Development Status :: 4 - Beta
Classifier: Intended Audience :: Developers
Classifier: Operating System :: OS Independent
Classifier: Programming Language :: Python :: 3
Classifier: Programming Language :: Python :: 3.7
Classifier: Programming Language :: Python :: 3.8
Classifier: Programming Language :: Python :: 3.9
Classifier: Programming Language :: Python :: 3.10
Classifier: Programming Language :: Python :: 3.11
Classifier: Programming Language :: Python :: 3.12
Classifier: Topic :: Internet :: WWW/HTTP
Classifier: Topic :: Software Development :: Libraries :: Python Modules
Classifier: Framework :: AsyncIO
Requires-Python: >=3.7
License-File: LICENSE
Requires-Dist: httpx[socks]>=0.23.0
Provides-Extra: dev
Requires-Dist: pytest>=7.0.0; extra == "dev"
Requires-Dist: pytest-asyncio>=0.21.0; extra == "dev"
Requires-Dist: pytest-cov>=4.0.0; extra == "dev"
Dynamic: license-file
